Action.py
Actions.py
Condition.py
Conditions.py
Event.py
ReadStateMachine.py
State.py
StateMachine.py
__init__.py
PyStateMachines-0.0.6.data/data/schema/StateMachine.xsd
PyStateMachines-0.0.6.dist-info/LICENSE
PyStateMachines-0.0.6.dist-info/METADATA
PyStateMachines-0.0.6.dist-info/WHEEL
PyStateMachines-0.0.6.dist-info/entry_points.txt
PyStateMachines-0.0.6.dist-info/top_level.txt
PyStateMachines-0.0.6.dist-info/RECORD
