Metadata-Version: 2.1
Name: PyStateMachines
Version: 0.0.6
Summary: PyStateMachines Package
Home-page: https://github.com/ZigRazor/PyStateMachine
Author: ZigRazor
Author-email: zigrazor@gmail.com
License: GNU GENERAL PUBLIC LICENSE
Project-URL: Changelog, https://github.com/ZigRazor/PyStateMachine/blob/master/CHANGELOG.md
Project-URL: Issue Tracker, https://github.com/ZigRazor/PyStateMachine/issues
Keywords: development,state,finite-state machine,automaton,state-machine
Platform: UNKNOWN
Classifier: Development Status :: 5 - Production/Stable
Classifier: Intended Audience :: Developers
Classifier: License :: OSI Approved :: GNU General Public License v3 (GPLv3)
Classifier: Operating System :: Unix
Classifier: Operating System :: POSIX
Classifier: Operating System :: Microsoft :: Windows
Classifier: Programming Language :: Python
Classifier: Programming Language :: Python :: 3
Classifier: Programming Language :: Python :: 3.5
Classifier: Programming Language :: Python :: 3.6
Classifier: Programming Language :: Python :: 3.7
Classifier: Programming Language :: Python :: 3.8
Classifier: Programming Language :: Python :: 3.9
Classifier: Topic :: Utilities
Classifier: Topic :: Software Development :: Libraries
Requires-Python: >=3
License-File: LICENSE
Requires-Dist: defusedxml (>=0.7.1)
Provides-Extra: defusedxml
Requires-Dist: defusedxml (>=0.7.1) ; extra == 'defusedxml'
